ampform_dpd/__init__.py
ampform_dpd/_attrs.py
ampform_dpd/angles.py
ampform_dpd/decay.py
ampform_dpd/py.typed
ampform_dpd/spin.py
ampform_dpd/version.py
ampform_dpd/adapter/__init__.py
ampform_dpd/adapter/qrules.py
ampform_dpd/dynamics/__init__.py
ampform_dpd/dynamics/builder.py
ampform_dpd/io/__init__.py
ampform_dpd/io/cached.py
ampform_dpd/io/serialization/__init__.py
ampform_dpd/io/serialization/amplitude.py
ampform_dpd/io/serialization/decay.py
ampform_dpd/io/serialization/dynamics.py
ampform_dpd/io/serialization/format.py
ampform_dpd-0.2.3.dist-info/LICENSE
ampform_dpd-0.2.3.dist-info/METADATA
ampform_dpd-0.2.3.dist-info/WHEEL
ampform_dpd-0.2.3.dist-info/top_level.txt
ampform_dpd-0.2.3.dist-info/RECORD
