Metadata-Version: 2.2
Name: ampform-dpd
Version: 0.2.3
Summary: Symbolic expressions for Dalitz-Plot Decomposition
Author-email: Common Partial Wave Analysis <compwa-admin@ep1.rub.de>
License:                                  Apache License
Project-URL: Changelog, https://github.com/ComPWA/ampform-dpd/releases
Project-URL: Documentation, https://compwa.github.io/ampform-dpd
Project-URL: Source, https://github.com/ComPWA/ampform-dpd
Project-URL: Tracker, https://github.com/ComPWA/ampform-dpd/issues
Classifier: Development Status :: 3 - Alpha
Classifier: Intended Audience :: Developers
Classifier: Intended Audience :: Education
Classifier: Intended Audience :: Science/Research
Classifier: License :: OSI Approved :: Apache Software License
Classifier: Natural Language :: English
Classifier: Operating System :: OS Independent
Classifier: Programming Language :: Python :: 3.10
Classifier: Programming Language :: Python :: 3.11
Classifier: Programming Language :: Python :: 3.12
Classifier: Programming Language :: Python :: 3.13
Classifier: Programming Language :: Python :: 3.9
Classifier: Programming Language :: Python
Classifier: Topic :: Scientific/Engineering :: Physics
Classifier: Topic :: Scientific/Engineering
Classifier: Typing :: Typed
Requires-Python: >=3.9
License-File: LICENSE
Requires-Dist: ampform>=0.15.7
Requires-Dist: attrs>=20.1.0
Requires-Dist: cloudpickle
Requires-Dist: frozendict
Requires-Dist: numpy
Requires-Dist: qrules>=0.10.0
Requires-Dist: sympy>=1.10
Requires-Dist: tensorwaves[jax]
Requires-Dist: typing-extensions; python_version < "3.11.0"
Provides-Extra: numba
Requires-Dist: tensorwaves[numba]; extra == "numba"
Provides-Extra: tf
Requires-Dist: tensorwaves[tf]; extra == "tf"
